{
  "source": "ESPN match summaries",
  "updatedAt": "2026-06-16T07:09:49.405Z",
  "scoring": {
    "yellow": 1,
    "red": 3
  },
  "caveat": "Cards are parsed from ESPN match-summary event data. Yellow cards are worth 1 point and red cards are worth 3 points.",
  "diagnostics": {
    "updatedAt": "2026-06-16T07:09:46.492Z",
    "source": "ESPN site API scoreboard + match summaries",
    "scoreboardUrlsTried": [
      "https://site.api.espn.com/apis/site/v2/sports/soccer/fifa.world/scoreboard?limit=300",
      "https://site.api.espn.com/apis/site/v2/sports/soccer/fifa.world/scoreboard?dates=20260611&limit=300",
      "https://site.api.espn.com/apis/site/v2/sports/soccer/fifa.world/scoreboard?dates=20260612&limit=300",
      "https://site.api.espn.com/apis/site/v2/sports/soccer/fifa.world/scoreboard?dates=20260613&limit=300",
      "https://site.api.espn.com/apis/site/v2/sports/soccer/fifa.world/scoreboard?dates=20260614&limit=300",
      "https://site.api.espn.com/apis/site/v2/sports/soccer/fifa.world/scoreboard?dates=20260615&limit=300",
      "https://site.api.espn.com/apis/site/v2/sports/soccer/fifa.world/scoreboard?dates=20260616&limit=300",
      "https://site.api.espn.com/apis/site/v2/sports/soccer/fifa.world/scoreboard?dates=20260617&limit=300",
      "https://site.api.espn.com/apis/site/v2/sports/soccer/fifa.world/scoreboard?dates=20260618&limit=300",
      "https://site.api.espn.com/apis/site/v2/sports/soccer/fifa.world/scoreboard?dates=20260619&limit=300",
      "https://site.api.espn.com/apis/site/v2/sports/soccer/fifa.world/scoreboard?dates=20260620&limit=300",
      "https://site.api.espn.com/apis/site/v2/sports/soccer/fifa.world/scoreboard?dates=20260621&limit=300",
      "https://site.api.espn.com/apis/site/v2/sports/soccer/fifa.world/scoreboard?dates=20260622&limit=300",
      "https://site.api.espn.com/apis/site/v2/sports/soccer/fifa.world/scoreboard?dates=20260623&limit=300",
      "https://site.api.espn.com/apis/site/v2/sports/soccer/fifa.world/scoreboard?dates=20260624&limit=300",
      "https://site.api.espn.com/apis/site/v2/sports/soccer/fifa.world/scoreboard?dates=20260625&limit=300",
      "https://site.api.espn.com/apis/site/v2/sports/soccer/fifa.world/scoreboard?dates=20260626&limit=300",
      "https://site.api.espn.com/apis/site/v2/sports/soccer/fifa.world/scoreboard?dates=20260627&limit=300",
      "https://site.api.espn.com/apis/site/v2/sports/soccer/fifa.world/scoreboard?dates=20260628&limit=300",
      "https://site.api.espn.com/apis/site/v2/sports/soccer/fifa.world/scoreboard?dates=20260629&limit=300",
      "https://site.api.espn.com/apis/site/v2/sports/soccer/fifa.world/scoreboard?dates=20260630&limit=300",
      "https://site.api.espn.com/apis/site/v2/sports/soccer/fifa.world/scoreboard?dates=20260701&limit=300",
      "https://site.api.espn.com/apis/site/v2/sports/soccer/fifa.world/scoreboard?dates=20260702&limit=300",
      "https://site.api.espn.com/apis/site/v2/sports/soccer/fifa.world/scoreboard?dates=20260703&limit=300",
      "https://site.api.espn.com/apis/site/v2/sports/soccer/fifa.world/scoreboard?dates=20260704&limit=300",
      "https://site.api.espn.com/apis/site/v2/sports/soccer/fifa.world/scoreboard?dates=20260705&limit=300",
      "https://site.api.espn.com/apis/site/v2/sports/soccer/fifa.world/scoreboard?dates=20260706&limit=300",
      "https://site.api.espn.com/apis/site/v2/sports/soccer/fifa.world/scoreboard?dates=20260707&limit=300",
      "https://site.api.espn.com/apis/site/v2/sports/soccer/fifa.world/scoreboard?dates=20260708&limit=300",
      "https://site.api.espn.com/apis/site/v2/sports/soccer/fifa.world/scoreboard?dates=20260709&limit=300",
      "https://site.api.espn.com/apis/site/v2/sports/soccer/fifa.world/scoreboard?dates=20260710&limit=300",
      "https://site.api.espn.com/apis/site/v2/sports/soccer/fifa.world/scoreboard?dates=20260711&limit=300",
      "https://site.api.espn.com/apis/site/v2/sports/soccer/fifa.world/scoreboard?dates=20260712&limit=300",
      "https://site.api.espn.com/apis/site/v2/sports/soccer/fifa.world/scoreboard?dates=20260713&limit=300",
      "https://site.api.espn.com/apis/site/v2/sports/soccer/fifa.world/scoreboard?dates=20260714&limit=300",
      "https://site.api.espn.com/apis/site/v2/sports/soccer/fifa.world/scoreboard?dates=20260715&limit=300",
      "https://site.api.espn.com/apis/site/v2/sports/soccer/fifa.world/scoreboard?dates=20260716&limit=300",
      "https://site.api.espn.com/apis/site/v2/sports/soccer/fifa.world/scoreboard?dates=20260717&limit=300",
      "https://site.api.espn.com/apis/site/v2/sports/soccer/fifa.world/scoreboard?dates=20260718&limit=300",
      "https://site.api.espn.com/apis/site/v2/sports/soccer/fifa.world/scoreboard?dates=20260719&limit=300"
    ],
    "scoreboardCallsSucceeded": 40,
    "scoreboardCallsFailed": 0,
    "eventsFound": 104,
    "eventsChecked": 16,
    "summaryCallsSucceeded": 16,
    "summaryCallsFailed": 0,
    "cardEvents": [
      {
        "eventId": "760415",
        "sourceName": "keyEvents",
        "team": "South Africa",
        "type": "yellow",
        "minute": "17'",
        "text": "Teboho Mokoena (South Africa) is shown the yellow card for a bad foul."
      },
      {
        "eventId": "760415",
        "sourceName": "keyEvents",
        "team": "Mexico",
        "type": "yellow",
        "minute": "23'",
        "text": "Brian Gutiérrez (Mexico) is shown the yellow card for a bad foul."
      },
      {
        "eventId": "760415",
        "sourceName": "keyEvents",
        "team": "South Africa",
        "type": "red",
        "minute": "49'",
        "text": "Yaya Sithole (South Africa) is shown the red card."
      },
      {
        "eventId": "760415",
        "sourceName": "keyEvents",
        "team": "South Africa",
        "type": "yellow",
        "minute": "74'",
        "text": "Nkosinathi Sibisi (South Africa) is shown the yellow card for a bad foul."
      },
      {
        "eventId": "760415",
        "sourceName": "keyEvents",
        "team": "South Africa",
        "type": "red",
        "minute": "84'",
        "text": "Themba Zwane (South Africa) is shown the red card for violent conduct."
      },
      {
        "eventId": "760415",
        "sourceName": "keyEvents",
        "team": "Mexico",
        "type": "red",
        "minute": "90'+2'",
        "text": "César Montes (Mexico) is shown the red card."
      },
      {
        "eventId": "760414",
        "sourceName": "keyEvents",
        "team": "South Korea",
        "type": "yellow",
        "minute": "90'+6'",
        "text": "Lee Gi-Hyuk (Korea Republic) is shown the yellow card for a bad foul."
      },
      {
        "eventId": "760416",
        "sourceName": "keyEvents",
        "team": "Canada",
        "type": "yellow",
        "minute": "11'",
        "text": "Alistair Johnston (Canada) is shown the yellow card for a bad foul."
      },
      {
        "eventId": "760416",
        "sourceName": "keyEvents",
        "team": "Bosnia-Herzegovina",
        "type": "yellow",
        "minute": "45'",
        "text": "Ermedin Demirovic (Bosnia and Herzegovina) is shown the yellow card for a bad foul."
      },
      {
        "eventId": "760416",
        "sourceName": "keyEvents",
        "team": "Bosnia-Herzegovina",
        "type": "yellow",
        "minute": "45'+1'",
        "text": "Jovo Lukic (Bosnia and Herzegovina) is shown the yellow card for a bad foul."
      },
      {
        "eventId": "760416",
        "sourceName": "keyEvents",
        "team": "Canada",
        "type": "yellow",
        "minute": "53'",
        "text": "Luc De Fougerolles (Canada) is shown the yellow card for a bad foul."
      },
      {
        "eventId": "760416",
        "sourceName": "keyEvents",
        "team": "Bosnia-Herzegovina",
        "type": "yellow",
        "minute": "90'+3'",
        "text": "Nikola Katic (Bosnia and Herzegovina) is shown the yellow card for a bad foul."
      },
      {
        "eventId": "760417",
        "sourceName": "keyEvents",
        "team": "Paraguay",
        "type": "yellow",
        "minute": "10'",
        "text": "Juan José Cáceres (Paraguay) is shown the yellow card for a bad foul."
      },
      {
        "eventId": "760417",
        "sourceName": "keyEvents",
        "team": "Paraguay",
        "type": "yellow",
        "minute": "53'",
        "text": "Miguel Almirón (Paraguay) is shown the yellow card."
      },
      {
        "eventId": "760417",
        "sourceName": "keyEvents",
        "team": "United States",
        "type": "yellow",
        "minute": "59'",
        "text": "Tyler Adams (USA) is shown the yellow card for a bad foul."
      },
      {
        "eventId": "760417",
        "sourceName": "keyEvents",
        "team": "Paraguay",
        "type": "yellow",
        "minute": "79'",
        "text": "Diego Gómez (Paraguay) is shown the yellow card for a bad foul."
      },
      {
        "eventId": "760417",
        "sourceName": "keyEvents",
        "team": "Paraguay",
        "type": "yellow",
        "minute": "88'",
        "text": "Álex Arce (Paraguay) is shown the yellow card for a bad foul."
      },
      {
        "eventId": "760417",
        "sourceName": "keyEvents",
        "team": "Paraguay",
        "type": "yellow",
        "minute": "90'+3'",
        "text": "Júnior Alonso (Paraguay) is shown the yellow card for a bad foul."
      },
      {
        "eventId": "760420",
        "sourceName": "keyEvents",
        "team": "Qatar",
        "type": "yellow",
        "minute": "16'",
        "text": "Mahmoud Abunada (Qatar) is shown the yellow card."
      },
      {
        "eventId": "760420",
        "sourceName": "keyEvents",
        "team": "Qatar",
        "type": "yellow",
        "minute": "23'",
        "text": "Jassem Gaber (Qatar) is shown the yellow card for a bad foul."
      },
      {
        "eventId": "760420",
        "sourceName": "keyEvents",
        "team": "Switzerland",
        "type": "yellow",
        "minute": "42'",
        "text": "Denis Zakaria (Switzerland) is shown the yellow card for a bad foul."
      },
      {
        "eventId": "760419",
        "sourceName": "keyEvents",
        "team": "Brazil",
        "type": "yellow",
        "minute": "37'",
        "text": "Casemiro (Brazil) is shown the yellow card for a bad foul."
      },
      {
        "eventId": "760419",
        "sourceName": "keyEvents",
        "team": "Brazil",
        "type": "yellow",
        "minute": "43'",
        "text": "Roger Ibañez (Brazil) is shown the yellow card for a bad foul."
      },
      {
        "eventId": "760418",
        "sourceName": "keyEvents",
        "team": "Haiti",
        "type": "yellow",
        "minute": "39'",
        "text": "Jean-Ricner Bellegarde (Haiti) is shown the yellow card for a bad foul."
      },
      {
        "eventId": "760418",
        "sourceName": "keyEvents",
        "team": "Scotland",
        "type": "yellow",
        "minute": "46'",
        "text": "Aaron Hickey (Scotland) is shown the yellow card for a bad foul."
      },
      {
        "eventId": "760418",
        "sourceName": "keyEvents",
        "team": "Scotland",
        "type": "yellow",
        "minute": "90'+1'",
        "text": "Findlay Curtis (Scotland) is shown the yellow card for a bad foul."
      },
      {
        "eventId": "760418",
        "sourceName": "keyEvents",
        "team": "Scotland",
        "type": "yellow",
        "minute": "90'+5'",
        "text": "Kenny McLean (Scotland) is shown the yellow card for a bad foul."
      },
      {
        "eventId": "760421",
        "sourceName": "keyEvents",
        "team": "Türkiye",
        "type": "yellow",
        "minute": "86'",
        "text": "Yunus Akgün (Türkiye) is shown the yellow card for a bad foul."
      },
      {
        "eventId": "760425",
        "sourceName": "keyEvents",
        "team": "Netherlands",
        "type": "yellow",
        "minute": "61'",
        "text": "Crysencio Summerville (Netherlands) is shown the yellow card for a bad foul."
      },
      {
        "eventId": "760425",
        "sourceName": "keyEvents",
        "team": "Netherlands",
        "type": "yellow",
        "minute": "83'",
        "text": "Memphis Depay (Netherlands) is shown the yellow card for a bad foul."
      },
      {
        "eventId": "760425",
        "sourceName": "keyEvents",
        "team": "Netherlands",
        "type": "yellow",
        "minute": "90'+1'",
        "text": "Micky van de Ven (Netherlands) is shown the yellow card for a bad foul."
      },
      {
        "eventId": "760423",
        "sourceName": "keyEvents",
        "team": "Ivory Coast",
        "type": "yellow",
        "minute": "28'",
        "text": "Seko Fofana (Côte d'Ivoire) is shown the yellow card for a bad foul."
      },
      {
        "eventId": "760423",
        "sourceName": "keyEvents",
        "team": "Ivory Coast",
        "type": "yellow",
        "minute": "38'",
        "text": "Franck Kessie (Côte d'Ivoire) is shown the yellow card for a bad foul."
      },
      {
        "eventId": "760423",
        "sourceName": "keyEvents",
        "team": "Ivory Coast",
        "type": "yellow",
        "minute": "40'",
        "text": "Guéla Doué (Côte d'Ivoire) is shown the yellow card for a bad foul."
      },
      {
        "eventId": "760423",
        "sourceName": "keyEvents",
        "team": "Ecuador",
        "type": "yellow",
        "minute": "73'",
        "text": "Jackson Porozo (Ecuador) is shown the yellow card for a bad foul."
      },
      {
        "eventId": "760424",
        "sourceName": "keyEvents",
        "team": "Tunisia",
        "type": "yellow",
        "minute": "54'",
        "text": "Rani Khedira (Tunisia) is shown the yellow card for a bad foul."
      }
    ],
    "unmatchedCardEvents": [
      {
        "eventId": "760428",
        "sourceName": "keyEvents",
        "rawTeam": "Cape Verde",
        "text": "Sidny Cabral (Cabo Verde) is shown the yellow card for a bad foul.",
        "type": "yellow"
      },
      {
        "eventId": "760428",
        "sourceName": "keyEvents",
        "rawTeam": "Spain",
        "text": "Pedri (Spain) is shown the yellow card for a bad foul.",
        "type": "yellow"
      },
      {
        "eventId": "760426",
        "sourceName": "keyEvents",
        "rawTeam": "Egypt",
        "text": "Marwan Attia (Egypt) is shown the yellow card for a bad foul.",
        "type": "yellow"
      },
      {
        "eventId": "760426",
        "sourceName": "keyEvents",
        "rawTeam": "Belgium",
        "text": "Timothy Castagne (Belgium) is shown the yellow card for a bad foul.",
        "type": "yellow"
      },
      {
        "eventId": "760426",
        "sourceName": "keyEvents",
        "rawTeam": "Egypt",
        "text": "Ahmed Fatouh (Egypt) is shown the yellow card for a bad foul.",
        "type": "yellow"
      },
      {
        "eventId": "760426",
        "sourceName": "keyEvents",
        "rawTeam": "Belgium",
        "text": "Maxim De Cuyper (Belgium) is shown the yellow card for a bad foul.",
        "type": "yellow"
      },
      {
        "eventId": "760429",
        "sourceName": "keyEvents",
        "rawTeam": "Saudi Arabia",
        "text": "Abdulelah Al Amri (Saudi Arabia) is shown the yellow card for a bad foul.",
        "type": "yellow"
      },
      {
        "eventId": "760427",
        "sourceName": "keyEvents",
        "rawTeam": "Iran",
        "text": "Ehsan Hajisafi (IR Iran) is shown the yellow card for a bad foul.",
        "type": "yellow"
      }
    ],
    "warnings": [
      "Skipped VAR-overturned card in 760417 (keyEvents): VAR Decision: Card Changed."
    ],
    "rowsMapped": 17,
    "nonZeroRows": 17
  },
  "cards": {
    "South Africa": {
      "yellow": 2,
      "secondYellow": 0,
      "straightRed": 2
    },
    "Paraguay": {
      "yellow": 5,
      "secondYellow": 0,
      "straightRed": 0
    },
    "Mexico": {
      "yellow": 1,
      "secondYellow": 0,
      "straightRed": 1
    },
    "Ivory Coast": {
      "yellow": 3,
      "secondYellow": 0,
      "straightRed": 0
    },
    "Scotland": {
      "yellow": 3,
      "secondYellow": 0,
      "straightRed": 0
    },
    "Bosnia-Herzegovina": {
      "yellow": 3,
      "secondYellow": 0,
      "straightRed": 0
    },
    "Netherlands": {
      "yellow": 3,
      "secondYellow": 0,
      "straightRed": 0
    },
    "Qatar": {
      "yellow": 2,
      "secondYellow": 0,
      "straightRed": 0
    },
    "Canada": {
      "yellow": 2,
      "secondYellow": 0,
      "straightRed": 0
    },
    "Brazil": {
      "yellow": 2,
      "secondYellow": 0,
      "straightRed": 0
    },
    "Haiti": {
      "yellow": 1,
      "secondYellow": 0,
      "straightRed": 0
    },
    "United States": {
      "yellow": 1,
      "secondYellow": 0,
      "straightRed": 0
    },
    "Tunisia": {
      "yellow": 1,
      "secondYellow": 0,
      "straightRed": 0
    },
    "Switzerland": {
      "yellow": 1,
      "secondYellow": 0,
      "straightRed": 0
    },
    "Türkiye": {
      "yellow": 1,
      "secondYellow": 0,
      "straightRed": 0
    },
    "South Korea": {
      "yellow": 1,
      "secondYellow": 0,
      "straightRed": 0
    },
    "Ecuador": {
      "yellow": 1,
      "secondYellow": 0,
      "straightRed": 0
    },
    "Curaçao": {
      "yellow": 0,
      "secondYellow": 0,
      "straightRed": 0
    },
    "Morocco": {
      "yellow": 0,
      "secondYellow": 0,
      "straightRed": 0
    },
    "Australia": {
      "yellow": 0,
      "secondYellow": 0,
      "straightRed": 0
    },
    "Japan": {
      "yellow": 0,
      "secondYellow": 0,
      "straightRed": 0
    },
    "Germany": {
      "yellow": 0,
      "secondYellow": 0,
      "straightRed": 0
    },
    "Sweden": {
      "yellow": 0,
      "secondYellow": 0,
      "straightRed": 0
    },
    "Czechia": {
      "yellow": 0,
      "secondYellow": 0,
      "straightRed": 0
    }
  }
}
